conftest.py
azure_helper/__init__.py
azure_helper/logger.py
azure_helper/interfaces/__init__.py
azure_helper/interfaces/aml_interface.py
azure_helper/interfaces/aml_interface_v2.py
azure_helper/interfaces/blob_storage_interface.py
azure_helper/steps/__init__.py
azure_helper/steps/create_aml_env.py
azure_helper/steps/create_aml_env_v2.py
azure_helper/steps/create_aml_experiment.py
azure_helper/steps/create_aml_experiment_v2.py
azure_helper/steps/create_data.py
azure_helper/steps/train.py
docs/includes/diagrams/dependencies.py
azure_mlops_helper-0.6.6.dist-info/METADATA
azure_mlops_helper-0.6.6.dist-info/WHEEL
azure_mlops_helper-0.6.6.dist-info/licenses/LICENSE.txt
azure_mlops_helper-0.6.6.dist-info/RECORD
